pyhandle/__init__.py
pyhandle/batchhsexceptions.py
pyhandle/clientcredentials.py
pyhandle/compatibility_helper.py
pyhandle/dbhsexceptions.py
pyhandle/handleclient.py
pyhandle/handleexceptions.py
pyhandle/handlesystemconnector.py
pyhandle/hsresponses.py
pyhandle/pyhandleclient.py
pyhandle/searcher.py
pyhandle/utilhandle.py
pyhandle/client/__init__.py
pyhandle/client/batchhandleclient.py
pyhandle/client/dbhandleclient.py
pyhandle/client/resthandleclient.py
pyhandle/tests/__init__.py
pyhandle/tests/main_test_script.py
pyhandle/tests/mockresponses.py
pyhandle/tests/test_script.py
pyhandle/tests/utilities.py
pyhandle/tests/resources/handlerecord_for_reading_PUBLIC.json
pyhandle/tests/resources/handlerecord_with_10320LOC_PUBLIC.json
pyhandle/tests/resources/handlerecord_with_empty_10320LOC_PUBLIC.json
pyhandle/tests/resources/handlerecord_without_10320LOC_PUBLIC.json
pyhandle/tests/resources/testvalues_for_clientcredentials_tests_PUBLIC.json
pyhandle/tests/resources/testvalues_for_integration_tests_template_PUBLIC.json
pyhandle/tests/testcases/__init__.py
pyhandle/tests/testcases/clientcredentials_unit_test.py
pyhandle/tests/testcases/handleclient_2_read_patched_unit_test.py
pyhandle/tests/testcases/handleclient_read_integration_test.py
pyhandle/tests/testcases/handleclient_read_patched_unit_test.py
pyhandle/tests/testcases/handleclient_search_integration_test.py
pyhandle/tests/testcases/handleclient_search_unit_test.py
pyhandle/tests/testcases/handleclient_unit_test.py
pyhandle/tests/testcases/handleclient_write_integration_test.py
pyhandle/tests/testcases/handleclient_write_patched_unit_test.py
pyhandle/tests/testcases/handleconnector_patched_unit_test.py
pyhandle/tests/testcases/handleconnector_unit_test.py
pyhandle/tests/testcases/utilconfig_unit_test.py
pyhandle/tests/testcredentials/credentials_brokensyntax_PUBLIC.json
pyhandle/tests/testcredentials/credentials_clientempty_PUBLIC.json
pyhandle/tests/testcredentials/credentials_clientmissing_PUBLIC.json
pyhandle-1.5.0.dist-info/LICENSE
pyhandle-1.5.0.dist-info/METADATA
pyhandle-1.5.0.dist-info/NOTICE
pyhandle-1.5.0.dist-info/WHEEL
pyhandle-1.5.0.dist-info/top_level.txt
pyhandle-1.5.0.dist-info/RECORD
