Metadata-Version: 2.1
Name: pyhandle
Version: 1.5.0
Summary: Library for management of handles 
Home-page: UNKNOWN
License: Apache License 2.0
Download-URL: https://github.com/EUDAT-B2SAFE/PYHANDLE
Keywords: handles,PIDs
Platform: UNKNOWN
Classifier: Development Status :: 1 - Planning
Classifier: Programming Language :: Python :: 3
Classifier: Programming Language :: Python :: 3.6
Classifier: Programming Language :: Python :: 3.7
Classifier: Programming Language :: Python :: 3.8
Classifier: Programming Language :: Python :: 3.9
Classifier: Programming Language :: Python :: 3.10
Classifier: Programming Language :: Python :: 3.11
Classifier: Programming Language :: Python :: 3.12
Classifier: Programming Language :: Python :: 3.13
Classifier: License :: OSI Approved :: Apache Software License
Classifier: Intended Audience :: Developers
Classifier: Topic :: Software Development :: Libraries :: Python Modules
Requires-Python: >=3.6
Requires-Dist: datetime
Requires-Dist: future
Requires-Dist: six
Requires-Dist: pymysql==0.8.0; python_version < "2.8.0"
Requires-Dist: pymysql==0.8.0; python_version < "3.11.0"
Requires-Dist: requests==2.27.1; python_version == "3.6"
Requires-Dist: requests>=2.31.0; python_version > "3.6"
Requires-Dist: pymysql==1.1.0; python_version >= "3.11.0"
Requires-Dist: requests==2.25.1; python_version ~= "3.5.0"
